<?xml version="1.0" encoding="UTF-8"?>
<DATA VERSION="0.1">
	<VEDEGE SRCID="1" DSTID="5" TRAFFIC="15" DELAY="1" AFFTYPE="1" AT="pm01"/>
	<VEDEGE SRCID="2" DSTID="5" TRAFFIC="15" DELAY="3" AFFTYPE="1" AT="pm01"/>
	<VEDEGE SRCID="3" DSTID="6" TRAFFIC="15" DELAY="1" AFFTYPE="1" AT="pm01"/>
	<VEDEGE SRCID="1" DSTID="7" TRAFFIC="15" DELAY="3" AFFTYPE="1" AT="pm01"/>
	<VEDEGE SRCID="2" DSTID="6" TRAFFIC="15" DELAY="3" AFFTYPE="1" AT="pm01"/>
	<VEDEGE SRCID="8" DSTID="15" TRAFFIC="15" DELAY="3" AFFTYPE="1" AT="pm01"/>
	<VEDEGE SRCID="8" DSTID="17" TRAFFIC="15" DELAY="3" AFFTYPE="1" AT="pm01"/>
	<VEDEGE SRCID="9" DSTID="20" TRAFFIC="15" DELAY="3" AFFTYPE="1" AT="pm01"/>
	<VEDEGE SRCID="11" DSTID="18" TRAFFIC="15" DELAY="3" AFFTYPE="1" AT="pm01"/>
	<VEDEGE SRCID="11" DSTID="30" TRAFFIC="15" DELAY="3" AFFTYPE="1" AT="pm01"/>
	<VEDEGE SRCID="16" DSTID="21" TRAFFIC="15" DELAY="3" AFFTYPE="1" AT="pm01"/>
	<VEDEGE SRCID="18" DSTID="19" TRAFFIC="15" DELAY="3" AFFTYPE="1" AT="pm01"/>
	<VEDEGE SRCID="19" DSTID="25" TRAFFIC="15" DELAY="3" AFFTYPE="1" AT="pm01"/>
	<VEDEGE SRCID="19" DSTID="27" TRAFFIC="15" DELAY="3" AFFTYPE="1" AT="pm01"/>
</DATA>
